fortunae/__init__.py
fortunae/fortunae.py
fortunae-0.0.10.dist-info/LICENSE
fortunae-0.0.10.dist-info/METADATA
fortunae-0.0.10.dist-info/WHEEL
fortunae-0.0.10.dist-info/top_level.txt
fortunae-0.0.10.dist-info/RECORD
