Metadata-Version: 2.1
Name: fortunae
Version: 0.0.10
Summary: Fortunae quer ser tornar uma biblioteca de análise financeira. Indicada para importar indicadores fundamentalistas de ações e fundos
Home-page: UNKNOWN
Author: Arthur Chabole
Author-email: <chabole.arthur@gmail.com>
License: UNKNOWN
Keywords: python,finance,money,invest
Platform: UNKNOWN
Classifier: Development Status :: 1 - Planning
Classifier: Intended Audience :: Developers
Classifier: Programming Language :: Python :: 3
Classifier: Operating System :: Unix
Classifier: Operating System :: MacOS :: MacOS X
Classifier: Operating System :: Microsoft :: Windows
License-File: LICENSE
Requires-Dist: pandas
Requires-Dist: requests
